Metadata-Version: 2.1
Name: testflows.texts
Version: 1.8.211204.1053701
Summary: TestFlows - Texts
Home-page: https://github.com/testflows/testflows-texts
Author: Vitaliy Zakaznikov
Author-email: vzakaznikov@testflows.com
License: Apache-2.0
Platform: UNKNOWN
Classifier: Development Status :: 2 - Pre-Alpha
Classifier: Programming Language :: Python :: 3
Classifier: License :: OSI Approved :: Apache Software License
Classifier: Operating System :: POSIX :: Linux
Requires-Python: >=3.8
